AUTHORS.rst
CONTRIBUTING.rst
HISTORY.rst
LICENSE
MANIFEST.in
README.rst
setup.cfg
setup.py
django_easy_eddie.egg-info/PKG-INFO
django_easy_eddie.egg-info/SOURCES.txt
django_easy_eddie.egg-info/dependency_links.txt
django_easy_eddie.egg-info/not-zip-safe
django_easy_eddie.egg-info/requires.txt
django_easy_eddie.egg-info/top_level.txt
easy_eddie/__init__.py
easy_eddie/admin.py
easy_eddie/apps.py
easy_eddie/clients.py
easy_eddie/helpers.py
easy_eddie/managers.py
easy_eddie/models.py
easy_eddie/report_fetchers.py
easy_eddie/reports.py
easy_eddie/settings.py
easy_eddie/sms.py
easy_eddie/management/__init__.py
easy_eddie/management/commands/fetch_cloud_watch_log_events.py
easy_eddie/migrations/0001_initial.py
easy_eddie/migrations/0002_smsevent_event_name.py
easy_eddie/migrations/__init__.py