Metadata-Version: 1.1
Name: django-easy-eddie
Version: 0.1.1
Summary: This Django package sends your text messages (SMS) through Amazon SNS and provides reporting helpers.
Home-page: https://github.com/dreipol/django-easy-eddie
Author: dreipol GmbH
Author-email: dev@dreipol.ch
License: MIT
Keywords: django-easy-eddie
Platform: UNKNOWN
Classifier: Development Status :: 3 - Alpha
Classifier: Framework :: Django
Classifier: Framework :: Django :: 1.8
Classifier: Framework :: Django :: 1.9
Classifier: Framework :: Django :: 1.10
Classifier: Intended Audience :: Developers
Classifier: License :: OSI Approved :: BSD License
Classifier: Natural Language :: English
Classifier: Programming Language :: Python :: 3
Classifier: Programming Language :: Python :: 3.3
Classifier: Programming Language :: Python :: 3.4
Classifier: Programming Language :: Python :: 3.5
